blackjack_api/__init__.py
blackjack_api/blackjack.py
blackjack_api/card.py
blackjack_api/cli.py
blackjack_api/deck.py
blackjack_api/hand.py
blackjack_api/player.py
blackjack_api-1.1.0.dist-info/METADATA
blackjack_api-1.1.0.dist-info/WHEEL
blackjack_api-1.1.0.dist-info/licenses/LICENSE
blackjack_api-1.1.0.dist-info/RECORD
