Metadata-Version: 2.4
Name: blackjack-api
Version: 1.1.0
Summary: A 1-on-1 blackjack game library for simulating games, usable for any blackjack needs.
Project-URL: Homepage, https://github.com/EvanA4/blackjack-api
Project-URL: Issues, https://github.com/EvanA4/blackjack-api/issues
Author-email: Evan Abbott <evanabbott04@gmail.com>
License-Expression: MIT
License-File: LICENSE
Classifier: Operating System :: OS Independent
Classifier: Programming Language :: Python :: 3
Requires-Python: >=3.8
